eazyml/__init__.py
eazyml/Linux_x86_64/__init__.py
eazyml/Linux_x86_64/eazyml/__init__.cpython-310-x86_64-linux-gnu.so
eazyml/Linux_x86_64/eazyml/__init__.cpython-311-x86_64-linux-gnu.so
eazyml/Linux_x86_64/eazyml/__init__.cpython-312-x86_64-linux-gnu.so
eazyml/Linux_x86_64/eazyml/__init__.cpython-38-x86_64-linux-gnu.so
eazyml/Linux_x86_64/eazyml/__init__.cpython-39-x86_64-linux-gnu.so
eazyml/Linux_x86_64/eazyml/client.cpython-310-x86_64-linux-gnu.so
eazyml/Linux_x86_64/eazyml/client.cpython-311-x86_64-linux-gnu.so
eazyml/Linux_x86_64/eazyml/client.cpython-312-x86_64-linux-gnu.so
eazyml/Linux_x86_64/eazyml/client.cpython-38-x86_64-linux-gnu.so
eazyml/Linux_x86_64/eazyml/client.cpython-39-x86_64-linux-gnu.so
eazyml/Linux_x86_64/eazyml/globals/__init__.cpython-310-x86_64-linux-gnu.so
eazyml/Linux_x86_64/eazyml/globals/__init__.cpython-311-x86_64-linux-gnu.so
eazyml/Linux_x86_64/eazyml/globals/__init__.cpython-312-x86_64-linux-gnu.so
eazyml/Linux_x86_64/eazyml/globals/__init__.cpython-38-x86_64-linux-gnu.so
eazyml/Linux_x86_64/eazyml/globals/__init__.cpython-39-x86_64-linux-gnu.so
eazyml/Linux_x86_64/eazyml/globals/config.cpython-310-x86_64-linux-gnu.so
eazyml/Linux_x86_64/eazyml/globals/config.cpython-311-x86_64-linux-gnu.so
eazyml/Linux_x86_64/eazyml/globals/config.cpython-312-x86_64-linux-gnu.so
eazyml/Linux_x86_64/eazyml/globals/config.cpython-38-x86_64-linux-gnu.so
eazyml/Linux_x86_64/eazyml/globals/config.cpython-39-x86_64-linux-gnu.so
eazyml/Linux_x86_64/eazyml/globals/global_var.cpython-310-x86_64-linux-gnu.so
eazyml/Linux_x86_64/eazyml/globals/global_var.cpython-311-x86_64-linux-gnu.so
eazyml/Linux_x86_64/eazyml/globals/global_var.cpython-312-x86_64-linux-gnu.so
eazyml/Linux_x86_64/eazyml/globals/global_var.cpython-38-x86_64-linux-gnu.so
eazyml/Linux_x86_64/eazyml/globals/global_var.cpython-39-x86_64-linux-gnu.so
eazyml/Linux_x86_64/eazyml/globals/global_var_range.cpython-310-x86_64-linux-gnu.so
eazyml_automl-0.0.75.dist-info/LICENSE
eazyml_automl-0.0.75.dist-info/METADATA
eazyml_automl-0.0.75.dist-info/WHEEL
eazyml_automl-0.0.75.dist-info/top_level.txt
eazyml_automl-0.0.75.dist-info/RECORD
