Metadata-Version: 2.1
Name: eazyml-automl
Version: 0.0.75
Summary: EazyML provides a suite of APIs for training, testing and optimizing machine learning models with built-in AutoML capabilities, hyperparameter tuning, and cross-validation.
Home-page: https://eazyml.com/
Author: EazyML
Author-email: admin@ipsoftlabs.com
Project-URL: Documentation, https://docs.eazyml.com/
Project-URL: Homepage, https://eazyml.com/
Project-URL: Contact Us, https://eazyml.com/trust-in-ai
Project-URL: eazyml-automl, https://pypi.org/project/eazyml-automl/
Project-URL: eazyml-counterfactual, https://pypi.org/project/eazyml-counterfactual/
Project-URL: eazyml-xai, https://pypi.org/project/eazyml-xai/
Project-URL: eazyml-xai-image, https://pypi.org/project/eazyml-xai-image/
Project-URL: eazyml-insight, https://pypi.org/project/eazyml-insight/
Project-URL: eazyml-data-quality, https://pypi.org/project/eazyml-data-quality/
Keywords: auto-ml,automl,machine-learning,model-training,hyperparameter-tuning,feature-selection,cross-validation,confidence-score,ml-api,model-evaluation
Classifier: Development Status :: 5 - Production/Stable
Classifier: License :: Other/Proprietary License
Classifier: Intended Audience :: Education
Classifier: Intended Audience :: Developers
Classifier: Intended Audience :: Science/Research
Classifier: Intended Audience :: System Administrators
Classifier: Intended Audience :: Information Technology
Classifier: Programming Language :: Python :: 3.8
Classifier: Programming Language :: Python :: 3.9
Classifier: Programming Language :: Python :: 3.10
Classifier: Programming Language :: Python :: 3.11
Classifier: Programming Language :: Python :: 3.12
Classifier: Topic :: Scientific/Engineering :: Artificial Intelligence
Classifier: Operating System :: Unix
Classifier: Operating System :: MacOS
Classifier: Operating System :: Microsoft :: Windows
Classifier: Operating System :: POSIX :: Linux
Requires-Python: >=3.7
License-File: LICENSE
Requires-Dist: statsmodels
Requires-Dist: xgboost
Requires-Dist: cryptography
Requires-Dist: Werkzeug>=2.0.3
Requires-Dist: PyYAML
Requires-Dist: nltk
Requires-Dist: cachetools
Requires-Dist: pyspark
Requires-Dist: markupsafe>=2.0.1
Requires-Dist: unidecode
Requires-Dist: Jinja2
Requires-Dist: ipython
Requires-Dist: setuptools
Requires-Dist: pandas==1.3.*; python_version <= "3.7"
Requires-Dist: scikit-learn==1.0.*; python_version <= "3.7"
Requires-Dist: numpy==1.21.*; python_version <= "3.7"
Requires-Dist: psutil==5.9.*; python_version <= "3.7"
Requires-Dist: requests==2.32.*; python_version <= "3.7"
Requires-Dist: pandas>=2.2.3; python_version == "3.10"
Requires-Dist: scikit-learn==1.3.*; python_version == "3.10"
Requires-Dist: numpy==1.24.*; python_version == "3.10"
Requires-Dist: psutil; python_version == "3.10"
Requires-Dist: requests; python_version == "3.10"
Requires-Dist: pandas>=2.2.3; python_version == "3.11"
Requires-Dist: scikit-learn==1.3.*; python_version == "3.11"
Requires-Dist: numpy==1.24.*; python_version == "3.11"
Requires-Dist: psutil; python_version == "3.11"
Requires-Dist: requests; python_version == "3.11"
Requires-Dist: pandas>=2.0.3; python_version == "3.8"
Requires-Dist: scikit-learn==1.3.*; python_version == "3.8"
Requires-Dist: numpy==1.24.*; python_version == "3.8"
Requires-Dist: psutil==5.9.*; python_version == "3.8"
Requires-Dist: requests==2.32.*; python_version == "3.8"
Requires-Dist: pandas>=2.2.3; python_version == "3.9"
Requires-Dist: scikit-learn==1.3.*; python_version == "3.9"
Requires-Dist: numpy==1.24.*; python_version == "3.9"
Requires-Dist: psutil; python_version == "3.9"
Requires-Dist: requests; python_version == "3.9"
Requires-Dist: pandas>=2.2.3; python_version > "3.11"
Requires-Dist: scikit-learn==1.3.*; python_version > "3.11"
Requires-Dist: numpy; python_version > "3.11"
Requires-Dist: psutil; python_version > "3.11"
Requires-Dist: requests; python_version > "3.11"
